{
  "hash": "ba7cba19",
  "configHash": "191b8bad",
  "lockfileHash": "ff86989b",
  "browserHash": "27ab63ea",
  "optimized": {
    "react": {
      "src": "../../node_modules/react/index.js",
      "file": "react.js",
      "fileHash": "d5a38d32",
      "needsInterop": true
    },
    "react-dom/client": {
      "src": "../../node_modules/react-dom/client.js",
      "file": "react-dom_client.js",
      "fileHash": "53c859d2",
      "needsInterop": true
    },
    "react-router-dom": {
      "src": "../../node_modules/react-router-dom/dist/index.mjs",
      "file": "react-router-dom.js",
      "fileHash": "b6f8520e",
      "needsInterop": false
    }
  },
  "chunks": {
    "chunk-WZVU6G5Y": {
      "file": "chunk-WZVU6G5Y.js"
    },
    "chunk-Q462PRL3": {
      "file": "chunk-Q462PRL3.js"
    }
  }
}